Metadata-Version: 2.1
Name: pokedream
Version: 2.5.1
Summary: A discord.py extension including useful tools for bot development and debugging.
Home-page: https://github.com/Gorialis/pokedream
Download-URL: https://github.com/Gorialis/pokedream/archive/2.5.1.tar.gz
Author: Devon (Gorialis) R
License: MIT
Project-URL: Documentation, https://pokedream.readthedocs.io/en/latest/
Project-URL: Code, https://github.com/Gorialis/pokedream
Project-URL: Issue tracker, https://github.com/Gorialis/pokedream/issues
Keywords: pokedream discord.py discord cog repl extension
Classifier: Development Status :: 5 - Production/Stable
Classifier: Framework :: AsyncIO
Classifier: Intended Audience :: Developers
Classifier: License :: OSI Approved :: MIT License
Classifier: Natural Language :: English
Classifier: Operating System :: OS Independent
Classifier: Programming Language :: Python :: 3 :: Only
Classifier: Programming Language :: Python :: 3.10
Classifier: Programming Language :: Python :: 3.11
Classifier: Topic :: Communications :: Chat
Classifier: Topic :: Internet
Classifier: Topic :: Software Development :: Debuggers
Classifier: Topic :: Software Development :: Testing
Classifier: Topic :: Utilities
Requires-Python: >=3.10.0
Provides-Extra: discordpy
Provides-Extra: docs
Provides-Extra: procinfo
Provides-Extra: profiling
Provides-Extra: publish
Provides-Extra: test
Provides-Extra: voice
License-File: LICENSE
